emailer/__init__.py
emailer/exceptions.py
emailer/providers/__init__.py
emailer/providers/brevo_provider.py
emailer/providers/email_provider.py
emailer/templates/__init__.py
emailer/templates/email_template.py
path2dream/__init__.py
path2dream/emailer.py
path2dream/templates/__init__.py
path2dream/templates/branded_email_template.py
path2dream/templates/email_confirmation_template.py
path2dream/templates/error_report_template.py
path2dream/templates/purchase_confirmation_template.py
path2dream/templates/results_template.py
yid_emailer-0.1.15.dist-info/METADATA
yid_emailer-0.1.15.dist-info/WHEEL
yid_emailer-0.1.15.dist-info/top_level.txt
yid_emailer-0.1.15.dist-info/RECORD
